sabacan/__init__.py
sabacan/__main__.py
sabacan/plantuml.py
sabacan/redpen.py
sabacan/utils.py
sabacan-0.0.4.dist-info/LICENSE
sabacan-0.0.4.dist-info/METADATA
sabacan-0.0.4.dist-info/WHEEL
sabacan-0.0.4.dist-info/entry_points.txt
sabacan-0.0.4.dist-info/top_level.txt
sabacan-0.0.4.dist-info/RECORD
