Metadata-Version: 2.1
Name: sabacan
Version: 0.0.4
Summary: Command Line Interface for various application servers
Home-page: https://github.com/amedama41/sabacan
Author: amedama41
Author-email: kamo.devel41@gmail.com
License: UNKNOWN
Keywords: plantuml,redpen
Platform: UNKNOWN
Classifier: Environment :: Console
Classifier: License :: OSI Approved :: MIT License
Classifier: Programming Language :: Python :: 3
Classifier: Topic :: Utilities
Requires-Python: >=3.5
